commitgen/__init__.py
commitgen/__main__.py
commitgen/ai.py
commitgen/cli.py
commitgen/config.py
commitgen/constants.py
commitgen/git_utils.py
commitgen_tool-0.1.6.dist-info/licenses/LICENSE
tests/__init__.py
tests/test_ai.py
tests/test_cli.py
tests/test_config.py
tests/test_editor.py
tests/test_git_utils.py
commitgen_tool-0.1.6.dist-info/METADATA
commitgen_tool-0.1.6.dist-info/WHEEL
commitgen_tool-0.1.6.dist-info/entry_points.txt
commitgen_tool-0.1.6.dist-info/top_level.txt
commitgen_tool-0.1.6.dist-info/RECORD
