Metadata-Version: 2.4
Name: commitgen-tool
Version: 0.1.6
Summary: AI-powered Conventional Commit message generator for Git using OpenAI
License: MIT
Requires-Python: >=3.10
License-File: LICENSE
Requires-Dist: typer
Requires-Dist: python-dotenv
Requires-Dist: openai
Dynamic: license-file
